[{"zipcode":11368,"avg_home_value":457834.6144292359,"median_household_income":62254.0,"median_age":34.3},{"zipcode":11385,"avg_home_value":797132.8645251795,"median_household_income":77350.0,"median_age":36.2},{"zipcode":11208,"avg_home_value":669321.3076262424,"median_household_income":49679.0,"median_age":33.2},{"zipcode":11236,"avg_home_value":643293.4833042437,"median_household_income":73562.0,"median_age":39.1},{"zipcode":10467,"avg_home_value":328464.4227381598,"median_household_income":42639.0,"median_age":34.4},{"zipcode":11373,"avg_home_value":470100.7143932532,"median_household_income":62072.0,"median_age":37.4},{"zipcode":11226,"avg_home_value":703403.5174605794,"median_household_income":66173.0,"median_age":35.4},{"zipcode":11207,"avg_home_value":585003.5316398011,"median_household_income":45616.0,"median_age":35.0},{"zipcode":10025,"avg_home_value":967423.4753812852,"median_household_income":103440.0,"median_age":40.0},{"zipcode":11214,"avg_home_value":682309.9643924449,"median_household_income":58487.0,"median_age":40.5},{"zipcode":11234,"avg_home_value":732116.8346050605,"median_household_income":86185.0,"median_age":41.7},{"zipcode":10314,"avg_home_value":659685.2792515947,"median_household_income":94578.0,"median_age":42.1},{"zipcode":11220,"avg_home_value":633687.7102580082,"median_household_income":57046.0,"median_age":35.9},{"zipcode":11219,"avg_home_value":895792.8409975659,"median_household_income":44450.0,"median_age":26.2},{"zipcode":11206,"avg_home_value":837084.4230029345,"median_household_income":49013.0,"median_age":29.7},{"zipcode":11221,"avg_home_value":923624.27545986,"median_household_income":66923.0,"median_age":32.1},{"zipcode":10456,"avg_home_value":399390.1264715506,"median_household_income":31166.0,"median_age":32.5},{"zipcode":11223,"avg_home_value":1002721.9263206176,"median_household_income":57281.0,"median_age":37.9},{"zipcode":11230,"avg_home_value":790165.8085684601,"median_household_income":61017.0,"median_age":35.2},{"zipcode":10458,"avg_home_value":311253.1113550579,"median_household_income":38768.0,"median_age":29.7},{"zipcode":11377,"avg_home_value":511838.3517546072,"median_household_income":66325.0,"median_age":40.4},{"zipcode":11235,"avg_home_value":555799.207872596,"median_household_income":58669.0,"median_age":45.9},{"zipcode":11229,"avg_home_value":727882.9672651339,"median_household_income":69076.0,"median_age":41.0},{"zipcode":11233,"avg_home_value":830813.1100116872,"median_household_income":52380.0,"median_age":34.1},{"zipcode":10453,"avg_home_value":554413.830095612,"median_household_income":34860.0,"median_age":33.2},{"zipcode":11204,"avg_home_value":1028440.7108371372,"median_household_income":58850.0,"median_age":34.9},{"zipcode":10468,"avg_home_value":249592.9914157625,"median_household_income":40138.0,"median_age":33.3},{"zipcode":11355,"avg_home_value":551069.8628817775,"median_household_income":46963.0,"median_age":44.9},{"zipcode":11203,"avg_home_value":687704.1528401802,"median_household_income":61414.0,"median_age":41.1},{"zipcode":10457,"avg_home_value":436527.889674539,"median_household_income":38066.0,"median_age":30.6},{"zipcode":10452,"avg_home_value":263771.4041973439,"median_household_income":33877.0,"median_age":32.2},{"zipcode":10469,"avg_home_value":638015.8999395889,"median_household_income":70415.0,"median_age":40.3},{"zipcode":10029,"avg_home_value":682776.4000400044,"median_household_income":33901.0,"median_age":38.4},{"zipcode":11218,"avg_home_value":833866.6653982704,"median_household_income":81857.0,"median_age":36.4},{"zipcode":11212,"avg_home_value":601094.1133377008,"median_household_income":30733.0,"median_age":38.4},{"zipcode":10462,"avg_home_value":211855.3906379655,"median_household_income":59032.0,"median_age":35.5},{"zipcode":10002,"avg_home_value":927411.9470448722,"median_household_income":37093.0,"median_age":43.7},{"zipcode":10466,"avg_home_value":605340.2099496259,"median_household_income":62918.0,"median_age":37.2},{"zipcode":11375,"avg_home_value":480045.0059310165,"median_household_income":96321.0,"median_age":44.1},{"zipcode":11691,"avg_home_value":628558.0379591987,"median_household_income":54877.0,"median_age":32.1},{"zipcode":11215,"avg_home_value":1319118.7093586321,"median_household_income":156930.0,"median_age":37.0},{"zipcode":10463,"avg_home_value":321247.7707764849,"median_household_income":63048.0,"median_age":41.9},{"zipcode":11209,"avg_home_value":708047.1494987374,"median_household_income":84145.0,"median_age":40.5},{"zipcode":11213,"avg_home_value":921799.7912585816,"median_household_income":48896.0,"median_age":34.5},{"zipcode":11201,"avg_home_value":1225932.9714059851,"median_household_income":148282.0,"median_age":35.3},{"zipcode":11210,"avg_home_value":857035.1828430956,"median_household_income":77378.0,"median_age":37.7},{"zipcode":11372,"avg_home_value":404736.5454786149,"median_household_income":62910.0,"median_age":40.7},{"zipcode":11432,"avg_home_value":821031.4791578641,"median_household_income":66246.0,"median_age":38.4},{"zipcode":10027,"avg_home_value":776208.663533878,"median_household_income":58435.0,"median_age":31.0},{"zipcode":10472,"avg_home_value":623661.5431008345,"median_household_income":36730.0,"median_age":32.9},{"zipcode":11434,"avg_home_value":644147.9256141302,"median_household_income":66546.0,"median_age":40.3},{"zipcode":11211,"avg_home_value":1091816.1088662308,"median_household_income":89091.0,"median_age":31.5},{"zipcode":10312,"avg_home_value":699752.6599362451,"median_household_income":100875.0,"median_age":40.6},{"zipcode":10024,"avg_home_value":1360938.5877276014,"median_household_income":153177.0,"median_age":41.5},{"zipcode":10032,"avg_home_value":545515.9181453651,"median_household_income":55059.0,"median_age":37.1},{"zipcode":11216,"avg_home_value":1017008.4642847084,"median_household_income":84661.0,"median_age":34.2},{"zipcode":10023,"avg_home_value":1307115.4857244771,"median_household_income":136109.0,"median_age":43.2},{"zipcode":10033,"avg_home_value":567701.9208479588,"median_household_income":71630.0,"median_age":36.9},{"zipcode":11238,"avg_home_value":1101104.2965803582,"median_household_income":114427.0,"median_age":35.3},{"zipcode":11435,"avg_home_value":526569.4045987407,"median_household_income":71346.0,"median_age":36.2},{"zipcode":10460,"avg_home_value":392246.6297430031,"median_household_income":31504.0,"median_age":33.9},{"zipcode":10031,"avg_home_value":512836.7114845957,"median_household_income":57180.0,"median_age":35.4},{"zipcode":11225,"avg_home_value":931466.2020067543,"median_household_income":68542.0,"median_age":36.1},{"zipcode":10128,"avg_home_value":1039491.7948524144,"median_household_income":127919.0,"median_age":42.1},{"zipcode":10473,"avg_home_value":518734.1906081527,"median_household_income":48212.0,"median_age":38.0},{"zipcode":10009,"avg_home_value":919452.095309157,"median_household_income":77551.0,"median_age":37.0},{"zipcode":11354,"avg_home_value":614267.1393892464,"median_household_income":52273.0,"median_age":46.6},{"zipcode":10306,"avg_home_value":691139.8753323121,"median_household_income":88687.0,"median_age":42.5},{"zipcode":10003,"avg_home_value":1282302.6503150556,"median_household_income":137533.0,"median_age":32.0},{"zipcode":11420,"avg_home_value":683825.170769705,"median_household_income":89027.0,"median_age":39.9},{"zipcode":10451,"avg_home_value":330177.2855375042,"median_household_income":33945.0,"median_age":34.3},{"zipcode":10016,"avg_home_value":893571.8910350156,"median_household_income":136431.0,"median_age":32.7},{"zipcode":10461,"avg_home_value":665019.8316575629,"median_household_income":61087.0,"median_age":38.9},{"zipcode":10459,"avg_home_value":436672.4042768562,"median_household_income":36631.0,"median_age":33.2},{"zipcode":10011,"avg_home_value":1419295.0666535024,"median_household_income":139343.0,"median_age":42.8},{"zipcode":11205,"avg_home_value":872007.3000226676,"median_household_income":68607.0,"median_age":29.5},{"zipcode":11419,"avg_home_value":695247.1178020636,"median_household_income":84245.0,"median_age":41.0},{"zipcode":11237,"avg_home_value":814582.4335222882,"median_household_income":65908.0,"median_age":31.7},{"zipcode":11224,"avg_home_value":536372.7081919638,"median_household_income":37241.0,"median_age":48.2},{"zipcode":11374,"avg_home_value":410340.9792491219,"median_household_income":79221.0,"median_age":41.2},{"zipcode":11228,"avg_home_value":1114462.0605801044,"median_household_income":77189.0,"median_age":42.4},{"zipcode":10465,"avg_home_value":640996.9152138884,"median_household_income":80245.0,"median_age":39.5},{"zipcode":11413,"avg_home_value":670911.9913013857,"median_household_income":104236.0,"median_age":40.1},{"zipcode":10040,"avg_home_value":485791.9901075864,"median_household_income":54700.0,"median_age":39.6},{"zipcode":10305,"avg_home_value":666385.0793412233,"median_household_income":76833.0,"median_age":41.1},{"zipcode":10019,"avg_home_value":1128626.5110071879,"median_household_income":105538.0,"median_age":40.4},{"zipcode":11365,"avg_home_value":952995.1070799972,"median_household_income":73279.0,"median_age":42.1},{"zipcode":10028,"avg_home_value":1259998.5288922037,"median_household_income":149789.0,"median_age":40.4},{"zipcode":10304,"avg_home_value":644474.8702265564,"median_household_income":64539.0,"median_age":38.8},{"zipcode":11357,"avg_home_value":957962.2560722772,"median_household_income":88580.0,"median_age":46.6},{"zipcode":10034,"avg_home_value":440058.7364828378,"median_household_income":63851.0,"median_age":37.3},{"zipcode":11421,"avg_home_value":684710.7182615831,"median_household_income":76721.0,"median_age":39.0},{"zipcode":11217,"avg_home_value":1365618.7126971779,"median_household_income":133269.0,"median_age":35.5},{"zipcode":11249,"avg_home_value":1202171.6859049287,"median_household_income":77378.0,"median_age":38.5},{"zipcode":11412,"avg_home_value":663318.1748185459,"median_household_income":93429.0,"median_age":40.2},{"zipcode":11367,"avg_home_value":510914.8816292104,"median_household_income":71469.0,"median_age":37.1},{"zipcode":10455,"avg_home_value":399634.3937833598,"median_household_income":30741.0,"median_age":31.6},{"zipcode":10021,"avg_home_value":1218660.3294413798,"median_household_income":136060.0,"median_age":44.5},{"zipcode":11222,"avg_home_value":1181233.5533383323,"median_household_income":110385.0,"median_age":34.9},{"zipcode":11433,"avg_home_value":643751.4924516975,"median_household_income":68801.0,"median_age":34.4},{"zipcode":11231,"avg_home_value":1555537.4270188715,"median_household_income":121638.0,"median_age":36.7},{"zipcode":10454,"avg_home_value":739504.4375924058,"median_household_income":21846.0,"median_age":32.3},{"zipcode":11378,"avg_home_value":815318.9773476589,"median_household_income":85464.0,"median_age":39.5},{"zipcode":11379,"avg_home_value":847543.9872180602,"median_household_income":88672.0,"median_age":43.3},{"zipcode":10301,"avg_home_value":676911.8287004896,"median_household_income":78053.0,"median_age":39.0},{"zipcode":11105,"avg_home_value":1023531.9745684128,"median_household_income":93200.0,"median_age":36.2},{"zipcode":11364,"avg_home_value":624426.1578179919,"median_household_income":90970.0,"median_age":45.6},{"zipcode":11106,"avg_home_value":580072.3660431989,"median_household_income":71972.0,"median_age":35.9},{"zipcode":11358,"avg_home_value":1017758.411574994,"median_household_income":74854.0,"median_age":42.8},{"zipcode":10026,"avg_home_value":807692.4120534947,"median_household_income":65038.0,"median_age":35.7},{"zipcode":11418,"avg_home_value":689543.3396918842,"median_household_income":77708.0,"median_age":39.2},{"zipcode":10035,"avg_home_value":594971.2854288375,"median_household_income":32555.0,"median_age":36.3},{"zipcode":10309,"avg_home_value":741333.5110244317,"median_household_income":107500.0,"median_age":40.5},{"zipcode":11101,"avg_home_value":1013742.5913875286,"median_household_income":98920.0,"median_age":34.0},{"zipcode":11103,"avg_home_value":894904.7598463148,"median_household_income":82597.0,"median_age":35.2},{"zipcode":10022,"avg_home_value":1008622.8936395023,"median_household_income":156255.0,"median_age":49.3},{"zipcode":11422,"avg_home_value":664429.9169594584,"median_household_income":95945.0,"median_age":40.0},{"zipcode":10010,"avg_home_value":1254209.2449002969,"median_household_income":131635.0,"median_age":36.0},{"zipcode":11417,"avg_home_value":692744.1533023138,"median_household_income":78498.0,"median_age":35.6},{"zipcode":10030,"avg_home_value":650347.693938275,"median_household_income":42834.0,"median_age":37.6},{"zipcode":10014,"avg_home_value":1563894.8251901043,"median_household_income":136559.0,"median_age":39.2},{"zipcode":11423,"avg_home_value":749864.2321088699,"median_household_income":69386.0,"median_age":41.7},{"zipcode":11414,"avg_home_value":600350.7363131169,"median_household_income":86113.0,"median_age":46.2},{"zipcode":11369,"avg_home_value":797932.8867826414,"median_household_income":66132.0,"median_age":40.7},{"zipcode":11361,"avg_home_value":933577.2538261734,"median_household_income":93734.0,"median_age":44.4},{"zipcode":11232,"avg_home_value":622825.1595949491,"median_household_income":77031.0,"median_age":34.9},{"zipcode":10308,"avg_home_value":673303.4487240355,"median_household_income":116082.0,"median_age":42.8},{"zipcode":10065,"avg_home_value":1420414.8012167038,"median_household_income":152335.0,"median_age":37.7},{"zipcode":10013,"avg_home_value":3292580.9484553221,"median_household_income":137572.0,"median_age":39.6},{"zipcode":11102,"avg_home_value":621488.8819690936,"median_household_income":95478.0,"median_age":35.0},{"zipcode":10075,"avg_home_value":1026803.3628851748,"median_household_income":131372.0,"median_age":43.0},{"zipcode":10303,"avg_home_value":500854.5760653451,"median_household_income":69879.0,"median_age":34.6},{"zipcode":11429,"avg_home_value":669917.1434971081,"median_household_income":89318.0,"median_age":42.0},{"zipcode":11416,"avg_home_value":685797.4735819929,"median_household_income":76477.0,"median_age":36.2},{"zipcode":10036,"avg_home_value":959445.2825399678,"median_household_income":98177.0,"median_age":39.7},{"zipcode":10001,"avg_home_value":1665111.7776104638,"median_household_income":101409.0,"median_age":35.8},{"zipcode":11104,"avg_home_value":477820.9515393097,"median_household_income":81142.0,"median_age":38.7},{"zipcode":11356,"avg_home_value":796028.3768287216,"median_household_income":73318.0,"median_age":38.6},{"zipcode":10039,"avg_home_value":618124.8150977967,"median_household_income":50164.0,"median_age":35.8},{"zipcode":10310,"avg_home_value":636511.9121021144,"median_household_income":96161.0,"median_age":38.4},{"zipcode":11427,"avg_home_value":725170.1335451604,"median_household_income":84000.0,"median_age":43.5},{"zipcode":10012,"avg_home_value":2404092.0678836931,"median_household_income":117581.0,"median_age":35.2},{"zipcode":10471,"avg_home_value":396513.2407686909,"median_household_income":96368.0,"median_age":46.0},{"zipcode":11370,"avg_home_value":733985.5706930971,"median_household_income":67241.0,"median_age":38.5},{"zipcode":11428,"avg_home_value":712605.1673441775,"median_household_income":83417.0,"median_age":43.6},{"zipcode":11426,"avg_home_value":734412.8809125392,"median_household_income":102818.0,"median_age":44.1},{"zipcode":11694,"avg_home_value":870127.4141692378,"median_household_income":88643.0,"median_age":46.2},{"zipcode":11436,"avg_home_value":628814.3504309388,"median_household_income":78306.0,"median_age":37.1},{"zipcode":11692,"avg_home_value":560119.1020740977,"median_household_income":53498.0,"median_age":36.9},{"zipcode":11411,"avg_home_value":654453.6386441764,"median_household_income":108131.0,"median_age":46.3},{"zipcode":11360,"avg_home_value":573459.9381751949,"median_household_income":92851.0,"median_age":50.5},{"zipcode":10037,"avg_home_value":485950.2829089691,"median_household_income":48782.0,"median_age":39.1},{"zipcode":11415,"avg_home_value":327029.0245715103,"median_household_income":80360.0,"median_age":41.4},{"zipcode":11362,"avg_home_value":658797.9856963324,"median_household_income":100528.0,"median_age":50.2},{"zipcode":10017,"avg_home_value":660569.4703945075,"median_household_income":136112.0,"median_age":40.7},{"zipcode":10302,"avg_home_value":570269.5951146494,"median_household_income":73927.0,"median_age":35.4},{"zipcode":11239,"avg_home_value":615987.2649916654,"median_household_income":33736.0,"median_age":45.8},{"zipcode":10470,"avg_home_value":594409.8360835046,"median_household_income":70107.0,"median_age":39.3},{"zipcode":11004,"avg_home_value":613207.2830443376,"median_household_income":100174.0,"median_age":42.6},{"zipcode":11366,"avg_home_value":1021747.0432626952,"median_household_income":100781.0,"median_age":41.4},{"zipcode":10307,"avg_home_value":767885.1907057347,"median_household_income":117469.0,"median_age":42.6},{"zipcode":10044,"avg_home_value":862171.9005365791,"median_household_income":115294.0,"median_age":41.4},{"zipcode":10005,"avg_home_value":1059507.3059532896,"median_household_income":197188.0,"median_age":30.3},{"zipcode":10007,"avg_home_value":2944184.4222601182,"median_household_income":250001.0,"median_age":34.0},{"zipcode":10018,"avg_home_value":1305453.3166483417,"median_household_income":130457.0,"median_age":34.2},{"zipcode":10069,"avg_home_value":1828785.6583309548,"median_household_income":183178.0,"median_age":38.6},{"zipcode":10280,"avg_home_value":756030.9726101336,"median_household_income":178148.0,"median_age":45.0},{"zipcode":11363,"avg_home_value":1040651.8168337736,"median_household_income":98111.0,"median_age":49.6},{"zipcode":10282,"avg_home_value":2153481.502993077,"median_household_income":250001.0,"median_age":38.8},{"zipcode":10464,"avg_home_value":655831.8924715574,"median_household_income":118972.0,"median_age":47.4},{"zipcode":10006,"avg_home_value":1057516.8266813664,"median_household_income":200536.0,"median_age":31.9},{"zipcode":10004,"avg_home_value":1133366.4188474277,"median_household_income":216017.0,"median_age":33.9},{"zipcode":11693,"avg_home_value":499000.0,"median_household_income":64688.0,"median_age":40.0},{"zipcode":11005,"avg_home_value":384000.67,"median_household_income":60800.0,"median_age":86.0},{"zipcode":10474,"avg_home_value":434500.0,"median_household_income":33157.0,"median_age":30.6},{"zipcode":11697,"avg_home_value":1182500.0,"median_household_income":113047.0,"median_age":50.0},{"zipcode":10475,"avg_home_value":960000.52,"median_household_income":56327.0,"median_age":46.7},{"zipcode":11359,"avg_home_value":770000.8199999999,"median_household_income":100016.0,"median_age":40.2},{"zipcode":11109,"avg_home_value":662500.0,"median_household_income":160898.0,"median_age":34.5},{"zipcode":10038,"avg_home_value":1100000.0,"median_household_income":99924.0,"median_age":35.1},{"zipcode":"11693","avg_home_value":403836.0,"median_household_income":64688.0,"median_age":40.0},{"zipcode":"11005","avg_home_value":655877.67,"median_household_income":60800.0,"median_age":86.0},{"zipcode":"10474","avg_home_value":304911.0,"median_household_income":33157.0,"median_age":30.6},{"zipcode":"11697","avg_home_value":612345.0,"median_household_income":113047.0,"median_age":50.0},{"zipcode":"10475","avg_home_value":79612.52,"median_household_income":56327.0,"median_age":46.7},{"zipcode":"11359","avg_home_value":770000.8199999999,"median_household_income":100016.0,"median_age":40.2},{"zipcode":"11109","avg_home_value":662500.0,"median_household_income":160898.0,"median_age":34.5},{"zipcode":"10038","avg_home_value":800285.0,"median_household_income":99924.0,"median_age":35.1}]